{
  "family": "narrow_passage",
  "workspace": [
    0,
    10,
    0,
    4
  ],
  "start": [
    1.5,
    2.0,
    0.0
  ],
  "goal": [
    8.5,
    2.0,
    0.0
  ],
  "obstacles": [
    {
      "id": 0,
      "shape_type": "rectangle",
      "class_true": "forbidden",
      "vertices": [
        [
          4.2,
          0.4
        ],
        [
          4.9,
          0.4
        ],
        [
          4.9,
          1.8
        ],
        [
          4.2,
          1.8
        ]
      ]
    },
    {
      "id": 1,
      "shape_type": "rectangle",
      "class_true": "forbidden",
      "vertices": [
        [
          4.2,
          2.2
        ],
        [
          4.9,
          2.2
        ],
        [
          4.9,
          3.6
        ],
        [
          4.2,
          3.6
        ]
      ]
    },
    {
      "id": 2,
      "shape_type": "triangle",
      "class_true": "forbidden",
      "vertices": [
        [
          3.1514787081098445,
          3.4000701079132614
        ],
        [
          2.797656331205581,
          3.4623552341391894
        ],
        [
          2.868779260780396,
          2.804791732092703
        ]
      ]
    },
    {
      "id": 3,
      "shape_type": "triangle",
      "class_true": "fragile",
      "vertices": [
        [
          6.122798020040275,
          0.4022167247011267
        ],
        [
          5.4298526232220095,
          0.8170200132419309
        ],
        [
          5.374400231516855,
          0.10004568899514804
        ]
      ]
    },
    {
      "id": 4,
      "shape_type": "trapezoid",
      "class_true": "movable",
      "vertices": [
        [
          0.926857513564307,
          0.3509729295354306
        ],
        [
          1.4198568145783643,
          1.2024885832467909
        ],
        [
          0.6014551726547549,
          1.313036910982147
        ],
        [
          0.20367746334522785,
          0.6259893929069615
        ]
      ]
    },
    {
      "id": 5,
      "shape_type": "triangle",
      "class_true": "safe",
      "vertices": [
        [
          1.5514763561735538,
          3.273372375443342
        ],
        [
          1.1945340302525544,
          3.376017793697967
        ],
        [
          1.2243118722377135,
          2.634804383511556
        ]
      ]
    },
    {
      "id": 6,
      "shape_type": "circle",
      "class_true": "movable",
      "vertices": [
        [
          5.09275553709244,
          2.0268859396481496
        ],
        [
          5.107604556806211,
          2.0430153414936854
        ],
        [
          5.123476696982252,
          2.0581390366964736
        ],
        [
          5.140303990679592,
          2.072192263271824
        ],
        [
          5.158014380843249,
          2.085114843146051
        ],
        [
          5.176532028863592,
          2.0968514398482223
        ],
        [
          5.195777639328917,
          2.1073517954694236
        ],
        [
          5.2156687995805715,
          2.1165709458748414
        ],
        [
          5.236120332616612,
          2.1244694132470894
        ],
        [
          5.2570446618328015,
          2.131013375136286
        ],
        [
          5.278352186039074,
          2.1361748092929735
        ],
        [
          5.299951663145588,
          2.139931613663695
        ],
        [
          5.321750600875363,
          2.142267701035381
        ],
        [
          5.343655652830404,
          2.143173067923262
        ],
        [
          5.365573018215316,
          2.1426438374073307
        ],
        [
          5.387408843506704,
          2.1406822757339046
        ],
        [
          5.409069624348376,
          2.137296782611214
        ],
        [
          5.430462605951344,
          2.1325018552405606
        ],
        [
          5.451496180284071,
          2.1263180262370764
        ],
        [
          5.472080278352134,
          2.1187717757059126
        ],
        [
          5.492126755887476,
          2.1098954178503653
        ],
        [
          5.511549770795701,
          2.099726962597495
        ],
        [
          5.530266150745094,
          2.0883099528337845
        ],
        [
          5.548195749323323,
          2.0756932779478134
        ],
        [
          5.565261789236673,
          2.06193096447839
        ],
        [
          5.581391191082209,
          2.0470819447646194
        ],
        [
          5.5965148862849965,
          2.031209804588579
        ],
        [
          5.6105681128603475,
          2.0143825108912377
        ],
        [
          5.623490692734575,
          1.996672120727581
        ],
        [
          5.635227289436745,
          1.9781544727072382
        ],
        [
          5.6457276450579466,
          1.958908862241913
        ],
        [
          5.654946795463364,
          1.9390177019902586
        ],
        [
          5.662845262835613,
          1.9185661689542182
        ],
        [
          5.669389224724809,
          1.897641839738029
        ],
        [
          5.674550658881497,
          1.8763343155317562
        ],
        [
          5.678307463252218,
          1.8547348384252418
        ],
        [
          5.680643550623905,
          1.8329359006954673
        ],
        [
          5.681548917511785,
          1.8110308487404263
        ],
        [
          5.681019686995854,
          1.7891134833555147
        ],
        [
          5.6790581253224275,
          1.7672776580641256
        ],
        [
          5.6756726321997375,
          1.7456168772224538
        ],
        [
          5.670877704829084,
          1.7242238956194869
        ],
        [
          5.664693875825599,
          1.703190321286759
        ],
        [
          5.657147625294436,
          1.682606223218696
        ],
        [
          5.648271267438888,
          1.6625597456833536
        ],
        [
          5.638102812186019,
          1.6431367307751295
        ],
        [
          5.626685802422308,
          1.624420350825736
        ],
        [
          5.614069127536337,
          1.6064907522475074
        ],
        [
          5.600306814066913,
          1.5894247123341574
        ],
        [
          5.585457794353142,
          1.5732953104886216
        ],
        [
          5.569585654177102,
          1.5581716152858331
        ],
        [
          5.5527583604797615,
          1.5441183887104826
        ],
        [
          5.535047970316104,
          1.5311958088362556
        ],
        [
          5.516530322295762,
          1.5194592121340846
        ],
        [
          5.497284711830437,
          1.5089588565128833
        ],
        [
          5.477393551578782,
          1.4997397061074655
        ],
        [
          5.456942018542741,
          1.4918412387352171
        ],
        [
          5.436017689326553,
          1.4852972768460209
        ],
        [
          5.41471016512028,
          1.4801358426893334
        ],
        [
          5.393110688013765,
          1.4763790383186115
        ],
        [
          5.371311750283991,
          1.474042950946926
        ],
        [
          5.349406698328949,
          1.4731375840590446
        ],
        [
          5.327489332944038,
          1.473666814574976
        ],
        [
          5.305653507652649,
          1.4756283762484022
        ],
        [
          5.283992726810977,
          1.4790138693710926
        ],
        [
          5.26259974520801,
          1.4838087967417461
        ],
        [
          5.2415661708752825,
          1.4899926257452303
        ],
        [
          5.220982072807219,
          1.4975388762763941
        ],
        [
          5.200935595271877,
          1.5064152341319414
        ],
        [
          5.181512580363653,
          1.5165836893848117
        ],
        [
          5.16279620041426,
          1.5280006991485218
        ],
        [
          5.14486660183603,
          1.5406173740344933
        ],
        [
          5.1278005619226805,
          1.5543796875039169
        ],
        [
          5.111671160077145,
          1.5692287072176874
        ],
        [
          5.096547464874357,
          1.5851008473937278
        ],
        [
          5.082494238299006,
          1.6019281410910686
        ],
        [
          5.069571658424779,
          1.6196385312547255
        ],
        [
          5.057835061722608,
          1.6381561792750685
        ],
        [
          5.047334706101407,
          1.6574017897403934
        ],
        [
          5.038115555695989,
          1.6772929499920481
        ],
        [
          5.030217088323741,
          1.6977444830280883
        ],
        [
          5.023673126434544,
          1.7186688122442777
        ],
        [
          5.0185116922778565,
          1.7399763364505503
        ],
        [
          5.014754887907135,
          1.761575813557065
        ],
        [
          5.01241880053545,
          1.7833747512868392
        ],
        [
          5.011513433647568,
          1.8052798032418802
        ],
        [
          5.012042664163499,
          1.827197168626792
        ],
        [
          5.014004225836925,
          1.849032993918181
        ],
        [
          5.017389718959616,
          1.8706937747598529
        ],
        [
          5.0221846463302695,
          1.8920867563628196
        ],
        [
          5.028368475333754,
          1.9131203306955475
        ],
        [
          5.0359147258649175,
          1.9337044287636107
        ],
        [
          5.044791083720464,
          1.9537509062989529
        ],
        [
          5.054959538973335,
          1.9731739212071773
        ],
        [
          5.066376548737045,
          1.9918903011565705
        ],
        [
          5.078993223623017,
          2.0098198997347994
        ]
      ]
    },
    {
      "id": 7,
      "shape_type": "parallelogram",
      "class_true": "fragile",
      "vertices": [
        [
          2.9099554485518713,
          1.8850633127506797
        ],
        [
          2.6948716188730577,
          2.49289838425591
        ],
        [
          2.2113636300492865,
          2.6323215927691193
        ],
        [
          2.4264474597281,
          2.024486521263889
        ]
      ]
    },
    {
      "id": 8,
      "shape_type": "triangle",
      "class_true": "movable",
      "vertices": [
        [
          5.347112440047273,
          3.0675316101806662
        ],
        [
          5.533770677601368,
          3.7153493448873434
        ],
        [
          4.945345496478685,
          3.5590519351990624
        ]
      ]
    },
    {
      "id": 9,
      "shape_type": "trapezoid",
      "class_true": "safe",
      "vertices": [
        [
          8.216977187770917,
          0.263759833441631
        ],
        [
          8.715739767941056,
          0.5127884918716283
        ],
        [
          8.515793711364468,
          1.240664310219464
        ],
        [
          8.207711729755115,
          1.0868411373975155
        ]
      ]
    },
    {
      "id": 10,
      "shape_type": "triangle",
      "class_true": "forbidden",
      "vertices": [
        [
          5.7954478467358035,
          1.9712113789281172
        ],
        [
          6.094856077800304,
          2.7449511274630756
        ],
        [
          5.256946062098902,
          2.747259763665831
        ]
      ]
    }
  ],
  "seed": 3918057668
}