{
  "family": "perturbed",
  "workspace": [
    0,
    12,
    0,
    12
  ],
  "start": [
    1.2000000000000002,
    1.2000000000000002,
    0.0
  ],
  "goal": [
    10.8,
    10.8,
    0.0
  ],
  "obstacles": [
    {
      "id": 0,
      "shape_type": "trapezoid",
      "class_true": "fragile",
      "vertices": [
        [
          7.523201903356611,
          7.838039866542204
        ],
        [
          7.549198819937702,
          9.294615108621173
        ],
        [
          6.348172805928801,
          8.839086829567634
        ],
        [
          6.328847935207632,
          7.756338105847584
        ]
      ]
    },
    {
      "id": 1,
      "shape_type": "parallelogram",
      "class_true": "movable",
      "vertices": [
        [
          10.664362823715097,
          8.20323014901
        ],
        [
          10.124990248039328,
          9.293490109359087
        ],
        [
          8.654432921444968,
          9.591990076164496
        ],
        [
          9.193805497120737,
          8.501730115815409
        ]
      ]
    }
  ],
  "seed": 30233197
}