{
  "family": "sparse_clutter",
  "workspace": [
    0,
    12,
    0,
    12
  ],
  "start": [
    1.2000000000000002,
    1.2000000000000002,
    0.0
  ],
  "goal": [
    10.8,
    10.8,
    0.0
  ],
  "obstacles": [
    {
      "id": 0,
      "shape_type": "parallelogram",
      "class_true": "safe",
      "vertices": [
        [
          8.247627096253202,
          5.973159503544144
        ],
        [
          9.64703715015338,
          6.101840397187665
        ],
        [
          10.037359115949162,
          7.155738313594787
        ],
        [
          8.637949062048984,
          7.027057419951267
        ]
      ]
    },
    {
      "id": 1,
      "shape_type": "trapezoid",
      "class_true": "safe",
      "vertices": [
        [
          8.629367907251405,
          0.6561501095702127
        ],
        [
          9.609662767167912,
          2.4613804830963923
        ],
        [
          8.259876048741148,
          3.01185948939825
        ],
        [
          7.622516880962279,
          1.838151276118646
        ]
      ]
    },
    {
      "id": 2,
      "shape_type": "rectangle",
      "class_true": "forbidden",
      "vertices": [
        [
          8.118255864876469,
          10.209664804721841
        ],
        [
          6.699713425245056,
          11.178001105528498
        ],
        [
          6.258260507830215,
          10.531304603569014
        ],
        [
          7.676802947461628,
          9.562968302762357
        ]
      ]
    },
    {
      "id": 3,
      "shape_type": "trapezoid",
      "class_true": "movable",
      "vertices": [
        [
          7.28821807713705,
          9.81433619025993
        ],
        [
          5.654202631335446,
          10.929262295432082
        ],
        [
          5.156638291938991,
          10.178287694804746
        ],
        [
          6.382262681532948,
          9.342016146328882
        ]
      ]
    },
    {
      "id": 4,
      "shape_type": "triangle",
      "class_true": "movable",
      "vertices": [
        [
          1.9424786447280151,
          2.81407861732674
        ],
        [
          2.1907625084222353,
          3.644113505760389
        ],
        [
          0.9508016160706084,
          3.5105105146130455
        ]
      ]
    },
    {
      "id": 5,
      "shape_type": "trapezoid",
      "class_true": "safe",
      "vertices": [
        [
          2.8164969265988815,
          5.986652488639379
        ],
        [
          3.7826203496022384,
          6.802444121367861
        ],
        [
          2.652877653793389,
          8.255705719082835
        ],
        [
          2.023695126465136,
          7.7244259373984985
        ]
      ]
    },
    {
      "id": 6,
      "shape_type": "parallelogram",
      "class_true": "movable",
      "vertices": [
        [
          8.584503763113801,
          7.341558055965891
        ],
        [
          7.743647248097634,
          9.058618084854253
        ],
        [
          6.162494900567076,
          9.210573780713212
        ],
        [
          7.003351415583243,
          7.49351375182485
        ]
      ]
    }
  ],
  "seed": 2567201578
}